minecraftbotsapi/__init__.py
minecraftbotsapi-1.4.dist-info/METADATA
minecraftbotsapi-1.4.dist-info/WHEEL
minecraftbotsapi-1.4.dist-info/top_level.txt
minecraftbotsapi-1.4.dist-info/RECORD
