Metadata-Version: 2.1
Name: minecraftbotsapi
Version: 1.4
Summary: Функции для создания своего бота в Minecraft!
Author: florestdev
Author-email: florestone4185@internet.ru
Project-URL: Social Resources, https://taplink.cc/florestone4185
Project-URL: GitHub of Project, https://github.com/florestdev/minecraftbotsapi
Requires-Python: >=3.10
Requires-Dist: g4f==0.5.7.5
Requires-Dist: curl-cffi
Requires-Dist: openai
Requires-Dist: mcstatus
